bsx_py/__init__.py
bsx_py/client/__init__.py
bsx_py/client/rest/__init__.py
bsx_py/client/rest/account/__init__.py
bsx_py/client/rest/account/client.py
bsx_py/client/rest/account/types.py
bsx_py/client/rest/auth/__init__.py
bsx_py/client/rest/auth/client.py
bsx_py/client/rest/auth/types.py
bsx_py/client/rest/base.py
bsx_py/client/rest/market/__init__.py
bsx_py/client/rest/market/client.py
bsx_py/client/rest/market/types.py
bsx_py/common/__init__.py
bsx_py/common/acc_info.py
bsx_py/common/exception.py
bsx_py/common/lock.py
bsx_py/common/types/__init__.py
bsx_py/common/types/account.py
bsx_py/common/types/auth.py
bsx_py/common/types/base.py
bsx_py/common/types/market.py
bsx_py/helper/__init__.py
bsx_py/helper/acc_storage.py
bsx_py/helper/api_key_base_manager.py
bsx_py/helper/base.py
bsx_py/helper/chain_info.py
bsx_py/helper/secret_base_manager.py
bsx_py/helper/signature_base_manager.py
bsx_py/instance.py
bsx_py/typed_message.py
bsx_sdk_py-0.0.1b19.dist-info/METADATA
bsx_sdk_py-0.0.1b19.dist-info/WHEEL
bsx_sdk_py-0.0.1b19.dist-info/RECORD
